caic/__init__.py
caic/utils/__init__.py
caic/utils/cjson.py
caic/utils/logger.py
caic/utils/utils.py
caic_cbguo-0.1.0.dist-info/METADATA
caic_cbguo-0.1.0.dist-info/WHEEL
caic_cbguo-0.1.0.dist-info/top_level.txt
caic_cbguo-0.1.0.dist-info/RECORD
